job_generation_groovy
