Metadata-Version: 1.1
Name: ros-groovy-job-generation
Version: 0.2.9
Summary: build farm job generation for dry jobs
Home-page: http://www.ros.org/wiki/job_generation
Author: Wim Meeussen
Author-email: wim@hidof.com
License: BSD
Download-URL: http://pr.willowgarage.com/downloads/
Keywords: ROS
Platform: UNKNOWN
Classifier: Programming Language :: Python
Classifier: License :: OSI Approved :: BSD License
